winloop/__init__.py
winloop/_noop.py
winloop/_testbase.py
winloop/_version.py
winloop/cbhandles.pxd
winloop/cbhandles.pyx
winloop/dns.pyx
winloop/errors.pyx
winloop/loop.cp312-win32.pyd
winloop/loop.pxd
winloop/loop.pyi
winloop/loop.pyx
winloop/lru.pyx
winloop/pseudosock.pyx
winloop/py.typed
winloop/request.pxd
winloop/request.pyx
winloop/server.pxd
winloop/server.pyx
winloop/shlex.pxd
winloop/shlex.pyx
winloop/sslproto.pxd
winloop/sslproto.pyx
winloop/handles/async_.pxd
winloop/handles/async_.pyx
winloop/handles/basetransport.pxd
winloop/handles/basetransport.pyx
winloop/handles/check.pxd
winloop/handles/check.pyx
winloop/handles/fsevent.pxd
winloop/handles/fsevent.pyx
winloop/handles/handle.pxd
winloop/handles/handle.pyx
winloop/handles/idle.pxd
winloop/handles/idle.pyx
winloop/handles/pipe.pxd
winloop/handles/pipe.pyx
winloop/handles/poll.pxd
winloop/handles/poll.pyx
winloop/handles/process.pxd
winloop/handles/process.pyx
winloop/handles/stream.pxd
winloop/handles/stream.pyx
winloop/handles/streamserver.pxd
winloop/handles/streamserver.pyx
winloop/handles/tcp.pxd
winloop/handles/tcp.pyx
winloop/handles/timer.pxd
winloop/handles/timer.pyx
winloop/handles/udp.pxd
winloop/handles/udp.pyx
winloop/includes/__init__.py
winloop/includes/consts.pxi
winloop/includes/debug.pxd
winloop/includes/flowcontrol.pxd
winloop/includes/python.pxd
winloop/includes/stdlib.pxi
winloop/includes/system.pxd
winloop/includes/uv.pxd
winloop-0.5.0.dist-info/licenses/LICENSE-APACHE
winloop-0.5.0.dist-info/licenses/LICENSE-MIT
winloop-0.5.0.dist-info/METADATA
winloop-0.5.0.dist-info/WHEEL
winloop-0.5.0.dist-info/top_level.txt
winloop-0.5.0.dist-info/RECORD
