Metadata-Version: 2.4
Name: winloop
Version: 0.5.0
Summary: Windows version of uvloop
Author-email: Vizonex <VizonexBusiness@gmail.com>
License: MIT License
Project-URL: github, https://github.com/Vizonex/Winloop
Keywords: asyncio,networking
Classifier: Development Status :: 5 - Production/Stable
Classifier: Framework :: AsyncIO
Classifier: Intended Audience :: Developers
Classifier: License :: OSI Approved :: Apache Software License
Classifier: License :: OSI Approved :: MIT License
Classifier: Operating System :: POSIX
Classifier: Operating System :: MacOS :: MacOS X
Classifier: Operating System :: Microsoft :: Windows
Classifier: Programming Language :: Python :: 3 :: Only
Classifier: Programming Language :: Python :: 3.8
Classifier: Programming Language :: Python :: 3.9
Classifier: Programming Language :: Python :: 3.10
Classifier: Programming Language :: Python :: 3.11
Classifier: Programming Language :: Python :: 3.12
Classifier: Programming Language :: Python :: 3.13
Classifier: Programming Language :: Python :: Implementation :: CPython
Classifier: Topic :: System :: Networking
Requires-Python: >=3.9.0
License-File: LICENSE-APACHE
License-File: LICENSE-MIT
Provides-Extra: test
Requires-Dist: aiohttp>=3.10.5; extra == "test"
Requires-Dist: flake8<8,>=5; extra == "test"
Requires-Dist: psutil; extra == "test"
Requires-Dist: pycodestyle<2.15,>=2.9; extra == "test"
Requires-Dist: pyOpenSSL<25.4,>=23.0; extra == "test"
Requires-Dist: mypy>=0.800; extra == "test"
Provides-Extra: dev
Requires-Dist: setuptools>=60; extra == "dev"
Requires-Dist: Cython==3.2.4; extra == "dev"
Provides-Extra: docs
Requires-Dist: Sphinx<9.2.0,>=4.1.2; extra == "docs"
Requires-Dist: sphinxcontrib-asyncio~=0.3.0; extra == "docs"
Requires-Dist: sphinx_rtd_theme<3.1.0,>=0.5.2; extra == "docs"
Dynamic: license-file
